Metadata-Version: 2.1
Name: pachet
Version: 1.0.0
Summary: My First Package
Author: Kirill
Author-email: studentkrutoitipa@gmail.com
